Avular/__init__.py
Avular/GPIO/99-gpio.rules
Avular/GPIO/__init__.py
Avular/GPIO/gpio.py
Avular/GPIO/gpio_cdev.py
Avular/GPIO/gpio_event.py
Avular/GPIO/gpio_pin_data.py
avular_gpio-3.2.1.dist-info/licenses/LICENSE.txt
avular_gpio-3.2.1.dist-info/METADATA
avular_gpio-3.2.1.dist-info/WHEEL
avular_gpio-3.2.1.dist-info/top_level.txt
avular_gpio-3.2.1.dist-info/RECORD
