Metadata-Version: 2.4
Name: Avular.GPIO
Version: 3.2.1
Summary: A module to control Jetson GPIO channels
Home-page: https://github.com/avular-robotics/avular-gpio
Author: Avular
Author-email: support@avular.com
License: MIT
Keywords: Avular GPIO
Classifier: Operating System :: POSIX :: Linux
Classifier: License :: OSI Approved :: MIT License
Classifier: Intended Audience :: Developers
Classifier: Programming Language :: Python :: 3
Classifier: Topic :: Software Development
Classifier: Topic :: System :: Hardware
License-File: LICENSE.txt
Dynamic: author
Dynamic: author-email
Dynamic: classifier
Dynamic: description
Dynamic: description-content-type
Dynamic: home-page
Dynamic: keywords
Dynamic: license
Dynamic: license-file
Dynamic: summary
